Workbook
Name Sel_City: Dashboard!$N$8
Name Sel_CustType: Dashboard!$K$10
Name Sel_Dealer: Dashboard!$Q$8
Name Sel_Fuel: Dashboard!$H$10
Name Sel_Model: Dashboard!$B$10
Name Sel_Month: Dashboard!$E$8
Name Sel_Payment: Dashboard!$N$10
Name Sel_Region: Dashboard!$H$8
Name Sel_Segment: Dashboard!$E$10
Name Sel_State: Dashboard!$K$8
Name Sel_Year: Dashboard!$B$8
Name Slicer_Car_Model: #N/A
Name Slicer_City: #N/A
Name Slicer_Customer_Type: #N/A
Name Slicer_Fuel_Type: #N/A
Name Slicer_Month: #N/A
Name Slicer_Payment_Mode: #N/A
Name Slicer_Region: #N/A
Name Slicer_Segment: #N/A
Name Slicer_State: #N/A
Name Slicer_Year: #N/A

Sheet Dashboard
B2: S | D2: MARUTI SUZUKI SALES ANALYSIS DASHBOARD | T2: LAST REFRESHED
T3: =TEXT(TODAY(),"dd-mmm-yyyy") -> 12-Jul-2026
D4: Executive Sales Performance Overview | FY 2021 – FY 2025
B6: 🔍 INTERACTIVE FILTERS (select a value, or leave "All")
B7: Year | E7: Month | H7: Region | K7: State | N7: City | Q7: Dealer Name
B8: All | E8: All | H8: All | K8: All | N8: All | Q8: All
B9: Car Model | E9: Segment | H9: Fuel Type | K9: Customer Type | N9: Payment Mode
B10: All | E10: All | H10: All | K10: Corporate | N10: All
B12: 📊 KEY PERFORMANCE INDICATORS
B13: Total Revenue | G13: Total Profit | L13: Total Units Sold | Q13: Avg. Selling Price
B14: =SUMIFS('Raw Data'!$M$2:$M$3001,'Raw Data'!$T$2:$T$3001,1) -> 40255876438 | G14: =SUMIFS('Raw Data'!$O$2:$O$3001,'Raw Data'!$T$2:$T$3001,1) -> 4.8315477e+09 | L14: =SUMIFS('Raw Data'!$K$2:$K$3001,'Raw Data'!$T$2:$T$3001,1) -> 48982 | Q14: =IFERROR(AVERAGEIFS('Raw Data'!$L$2:$L$3001,'Raw Data'!$T$2:$T$3001,1),0) -> 819184.16
B17: Avg. Customer Rating | G17: Total Dealers | L17: Total Discount | Q17: Avg. Delivery Days
B18: =IFERROR(AVERAGEIFS('Raw Data'!$R$2:$R$3001,'Raw Data'!$T$2:$T$3001,1),0) -> 4.2619266 | G18: =SUMPRODUCT((COUNTIFS('Raw Data'!$G$2:$G$3001,'Raw Data'!$G$2:$G$3001,'Raw Data'!$T$2:$T$3001,1)>0)/COUNTIF('Raw Data'!$G$2:$G$3001,'Raw Data'!$G$2:$G$3001&"")) -> 8 | L18: =SUMIFS('Raw Data'!$N$2:$N$3001,'Raw Data'!$T$2:$T$3001,1) -> 42076900 | Q18: =IFERROR(AVERAGEIFS('Raw Data'!$S$2:$S$3001,'Raw Data'!$T$2:$T$3001,1),0) -> 11.68152
B21: 📈 SALES & PERFORMANCE ANALYTICS

Sheet Raw Data
A1: Date | B1: Year | C1: Month | D1: Region | E1: State | F1: City | G1: Dealer Name | H1: Car Model | I1: Segment | J1: Fuel Type | K1: Units Sold | L1: Selling Price | M1: Revenue | N1: Discount | O1: Profit | P1: Customer Type | Q1: Payment Mode | R1: Rating | S1: Delivery Days | T1: Match
A2: 44212 | B2: 2021 | C2: 1 | D2: South | E2: Karnataka | F2: Bengaluru | G2: Bengaluru Motors | H2: Celerio | I2: Hatchback | J2: CNG | K2: 59 | L2: 602577 | M2: 35552043 | N2: 9135 | O2: 3569621.4 | P2: Corporate | Q2: Loan | R2: 4.5 | S2: 8 | T2: =IF(AND(OR($B2=Sel_Year,Sel_Year="All"),OR($C2=Sel_Month,Sel_Month="All"),OR($D2=Sel_Region,Sel_Region="All"),OR($E2=Sel_State,Sel_State="All"),OR($F2=Sel_City,Sel_City="All"),OR($G2=Sel_Dealer,Sel_Dealer="All"),OR($H2=Sel_Model,Sel_Model="All"),OR($I2=Sel_Segment,Sel_Segment="All"),OR($J2=Sel_Fuel,Sel_Fuel="All"),OR($P2=Sel_CustType,Sel_CustType="All"),OR($Q2=Sel_Payment,Sel_Payment="All")),1,0) -> 1
A3: 44221 | B3: 2021 | C3: 1 | D3: West | E3: Maharashtra | F3: Mumbai | G3: Mumbai Motors | H3: Alto K10 | I3: Hatchback | J3: Petrol | K3: 6 | L3: 478544 | M3: 2871264 | N3: 30546 | O3: 329108.2 | P3: Individual | Q3: EMI | R3: 4.2 | S3: 9 | T3: =IF(AND(OR($B3=Sel_Year,Sel_Year="All"),OR($C3=Sel_Month,Sel_Month="All"),OR($D3=Sel_Region,Sel_Region="All"),OR($E3=Sel_State,Sel_State="All"),OR($F3=Sel_City,Sel_City="All"),OR($G3=Sel_Dealer,Sel_Dealer="All"),OR($H3=Sel_Model,Sel_Model="All"),OR($I3=Sel_Segment,Sel_Segment="All"),OR($J3=Sel_Fuel,Sel_Fuel="All"),OR($P3=Sel_CustType,Sel_CustType="All"),OR($Q3=Sel_Payment,Sel_Payment="All")),1,0) -> 0
A4: 44197 | B4: 2021 | C4: 1 | D4: West | E4: Maharashtra | F4: Mumbai | G4: Mumbai Motors | H4: Ertiga | I4: MPV | J4: CNG | K4: 6 | L4: 921462 | M4: 5528772 | N4: 6667 | O4: 729597.16 | P4: Corporate | Q4: EMI | R4: 3.8 | S4: 15 | T4: =IF(AND(OR($B4=Sel_Year,Sel_Year="All"),OR($C4=Sel_Month,Sel_Month="All"),OR($D4=Sel_Region,Sel_Region="All"),OR($E4=Sel_State,Sel_State="All"),OR($F4=Sel_City,Sel_City="All"),OR($G4=Sel_Dealer,Sel_Dealer="All"),OR($H4=Sel_Model,Sel_Model="All"),OR($I4=Sel_Segment,Sel_Segment="All"),OR($J4=Sel_Fuel,Sel_Fuel="All"),OR($P4=Sel_CustType,Sel_CustType="All"),OR($Q4=Sel_Payment,Sel_Payment="All")),1,0) -> 1
A5: 44214 | B5: 2021 | C5: 1 | D5: North | E5: Delhi | F5: Delhi | G5: Delhi Motors | H5: Grand Vitara | I5: SUV | J5: Hybrid | K5: 19 | L5: 1420049 | M5: 26980931 | N5: 33697 | O5: 4185642.5 | P5: Individual | Q5: Loan | R5: 3.8 | S5: 9 | T5: =IF(AND(OR($B5=Sel_Year,Sel_Year="All"),OR($C5=Sel_Month,Sel_Month="All"),OR($D5=Sel_Region,Sel_Region="All"),OR($E5=Sel_State,Sel_State="All"),OR($F5=Sel_City,Sel_City="All"),OR($G5=Sel_Dealer,Sel_Dealer="All"),OR($H5=Sel_Model,Sel_Model="All"),OR($I5=Sel_Segment,Sel_Segment="All"),OR($J5=Sel_Fuel,Sel_Fuel="All"),OR($P5=Sel_CustType,Sel_CustType="All"),OR($Q5=Sel_Payment,Sel_Payment="All")),1,0) -> 0
A6: 44200 | B6: 2021 | C6: 1 | D6: South | E6: Telangana | F6: Hyderabad | G6: Hyderabad Motors | H6: Dzire | I6: Sedan | J6: CNG | K6: 6 | L6: 757274 | M6: 4543644 | N6: 41467 | O6: 698699.24 | P6: Individual | Q6: EMI | R6: 5 | S6: 11 | T6: =IF(AND(OR($B6=Sel_Year,Sel_Year="All"),OR($C6=Sel_Month,Sel_Month="All"),OR($D6=Sel_Region,Sel_Region="All"),OR($E6=Sel_State,Sel_State="All"),OR($F6=Sel_City,Sel_City="All"),OR($G6=Sel_Dealer,Sel_Dealer="All"),OR($H6=Sel_Model,Sel_Model="All"),OR($I6=Sel_Segment,Sel_Segment="All"),OR($J6=Sel_Fuel,Sel_Fuel="All"),OR($P6=Sel_CustType,Sel_CustType="All"),OR($Q6=Sel_Payment,Sel_Payment="All")),1,0) -> 0
A7: 44210 | B7: 2021 | C7: 1 | D7: West | E7: Maharashtra | F7: Mumbai | G7: Mumbai Motors | H7: XL6 | I7: MPV | J7: Petrol | K7: 26 | L7: 1278692 | M7: 33245992 | N7: 37820 | O7: 5150311.1 | P7: Individual | Q7: Loan | R7: 3.9 | S7: 17 | T7: =IF(AND(OR($B7=Sel_Year,Sel_Year="All"),OR($C7=Sel_Month,Sel_Month="All"),OR($D7=Sel_Region,Sel_Region="All"),OR($E7=Sel_State,Sel_State="All"),OR($F7=Sel_City,Sel_City="All"),OR($G7=Sel_Dealer,Sel_Dealer="All"),OR($H7=Sel_Model,Sel_Model="All"),OR($I7=Sel_Segment,Sel_Segment="All"),OR($J7=Sel_Fuel,Sel_Fuel="All"),OR($P7=Sel_CustType,Sel_CustType="All"),OR($Q7=Sel_Payment,Sel_Payment="All")),1,0) -> 0
A8: 44222 | B8: 2021 | C8: 1 | D8: East | E8: West Bengal | F8: Kolkata | G8: Kolkata Motors | H8: Celerio | I8: Hatchback | J8: CNG | K8: 59 | L8: 552262 | M8: 32583458 | N8: 36472 | O8: 3239421.3 | P8: Corporate | Q8: Loan | R8: 4.5 | S8: 13 | T8: =IF(AND(OR($B8=Sel_Year,Sel_Year="All"),OR($C8=Sel_Month,Sel_Month="All"),OR($D8=Sel_Region,Sel_Region="All"),OR($E8=Sel_State,Sel_State="All"),OR($F8=Sel_City,Sel_City="All"),OR($G8=Sel_Dealer,Sel_Dealer="All"),OR($H8=Sel_Model,Sel_Model="All"),OR($I8=Sel_Segment,Sel_Segment="All"),OR($J8=Sel_Fuel,Sel_Fuel="All"),OR($P8=Sel_CustType,Sel_CustType="All"),OR($Q8=Sel_Payment,Sel_Payment="All")),1,0) -> 1
A9: 44202 | B9: 2021 | C9: 1 | D9: North | E9: Uttar Pradesh | F9: Lucknow | G9: Lucknow Motors | H9: Baleno | I9: Hatchback | J9: Petrol | K9: 33 | L9: 733500 | M9: 24205500 | N9: 38320 | O9: 2145442.4 | P9: Corporate | Q9: Loan | R9: 4.2 | S9: 2 | T9: =IF(AND(OR($B9=Sel_Year,Sel_Year="All"),OR($C9=Sel_Month,Sel_Month="All"),OR($D9=Sel_Region,Sel_Region="All"),OR($E9=Sel_State,Sel_State="All"),OR($F9=Sel_City,Sel_City="All"),OR($G9=Sel_Dealer,Sel_Dealer="All"),OR($H9=Sel_Model,Sel_Model="All"),OR($I9=Sel_Segment,Sel_Segment="All"),OR($J9=Sel_Fuel,Sel_Fuel="All"),OR($P9=Sel_CustType,Sel_CustType="All"),OR($Q9=Sel_Payment,Sel_Payment="All")),1,0) -> 1
A10: 44209 | B10: 2021 | C10: 1 | D10: South | E10: Telangana | F10: Hyderabad | G10: Hyderabad Motors | H10: Swift | I10: Hatchback | J10: Petrol | K10: 24 | L10: 666096 | M10: 15986304 | N10: 45292 | O10: 2037529.6 | P10: Individual | Q10: Cash | R10: 4.3 | S10: 2 | T10: =IF(AND(OR($B10=Sel_Year,Sel_Year="All"),OR($C10=Sel_Month,Sel_Month="All"),OR($D10=Sel_Region,Sel_Region="All"),OR($E10=Sel_State,Sel_State="All"),OR($F10=Sel_City,Sel_City="All"),OR($G10=Sel_Dealer,Sel_Dealer="All"),OR($H10=Sel_Model,Sel_Model="All"),OR($I10=Sel_Segment,Sel_Segment="All"),OR($J10=Sel_Fuel,Sel_Fuel="All"),OR($P10=Sel_CustType,Sel_CustType="All"),OR($Q10=Sel_Payment,Sel_Payment="All")),1,0) -> 0
A11: 44208 | B11: 2021 | C11: 1 | D11: South | E11: Tamil Nadu | F11: Chennai | G11: Chennai Motors | H11: Grand Vitara | I11: SUV | J11: Hybrid | K11: 60 | L11: 1405935 | M11: 84356100 | N11: 20215 | O11: 9477946.8 | P11: Corporate | Q11: Loan | R11: 4.9 | S11: 19 | T11: =IF(AND(OR($B11=Sel_Year,Sel_Year="All"),OR($C11=Sel_Month,Sel_Month="All"),OR($D11=Sel_Region,Sel_Region="All"),OR($E11=Sel_State,Sel_State="All"),OR($F11=Sel_City,Sel_City="All"),OR($G11=Sel_Dealer,Sel_Dealer="All"),OR($H11=Sel_Model,Sel_Model="All"),OR($I11=Sel_Segment,Sel_Segment="All"),OR($J11=Sel_Fuel,Sel_Fuel="All"),OR($P11=Sel_CustType,Sel_CustType="All"),OR($Q11=Sel_Payment,Sel_Payment="All")),1,0) -> 1
A12: 44213 | B12: 2021 | C12: 1 | D12: North | E12: Delhi | F12: Delhi | G12: Delhi Motors | H12: Fronx | I12: SUV | J12: Petrol | K12: 55 | L12: 926161 | M12: 50938855 | N12: 38587 | O12: 7372441.2 | P12: Individual | Q12: Loan | R12: 4.9 | S12: 17 | T12: =IF(AND(OR($B12=Sel_Year,Sel_Year="All"),OR($C12=Sel_Month,Sel_Month="All"),OR($D12=Sel_Region,Sel_Region="All"),OR($E12=Sel_State,Sel_State="All"),OR($F12=Sel_City,Sel_City="All"),OR($G12=Sel_Dealer,Sel_Dealer="All"),OR($H12=Sel_Model,Sel_Model="All"),OR($I12=Sel_Segment,Sel_Segment="All"),OR($J12=Sel_Fuel,Sel_Fuel="All"),OR($P12=Sel_CustType,Sel_CustType="All"),OR($Q12=Sel_Payment,Sel_Payment="All")),1,0) -> 0
A13: 44223 | B13: 2021 | C13: 1 | D13: North | E13: Uttar Pradesh | F13: Lucknow | G13: Lucknow Motors | H13: Celerio | I13: Hatchback | J13: CNG | K13: 40 | L13: 563096 | M13: 22523840 | N13: 38077 | O13: 2546815.7 | P13: Corporate | Q13: Loan | R13: 4 | S13: 19 | T13: =IF(AND(OR($B13=Sel_Year,Sel_Year="All"),OR($C13=Sel_Month,Sel_Month="All"),OR($D13=Sel_Region,Sel_Region="All"),OR($E13=Sel_State,Sel_State="All"),OR($F13=Sel_City,Sel_City="All"),OR($G13=Sel_Dealer,Sel_Dealer="All"),OR($H13=Sel_Model,Sel_Model="All"),OR($I13=Sel_Segment,Sel_Segment="All"),OR($J13=Sel_Fuel,Sel_Fuel="All"),OR($P13=Sel_CustType,Sel_CustType="All"),OR($Q13=Sel_Payment,Sel_Payment="All")),1,0) -> 1
... A3001: 45998 | B3001: 2025 | C3001: 12 | D3001: South | E3001: Tamil Nadu | F3001: Chennai | G3001: Chennai Motors | H3001: Celerio | I3001: Hatchback | J3001: CNG | K3001: 25 | L3001: 590708 | M3001: 14767700 | N3001: 24680 | O3001: 2125569.2 | P3001: Corporate | Q3001: Loan | R3001: 4.2 | S3001: 18 | T3001: =IF(AND(OR($B3001=Sel_Year,Sel_Year="All"),OR($C3001=Sel_Month,Sel_Month="All"),OR($D3001=Sel_Region,Sel_Region="All"),OR($E3001=Sel_State,Sel_State="All"),OR($F3001=Sel_City,Sel_City="All"),OR($G3001=Sel_Dealer,Sel_Dealer="All"),OR($H3001=Sel_Model,Sel_Model="All"),OR($I3001=Sel_Segment,Sel_Segment="All"),OR($J3001=Sel_Fuel,Sel_Fuel="All"),OR($P3001=Sel_CustType,Sel_CustType="All"),OR($Q3001=Sel_Payment,Sel_Payment="All")),1,0) -> 1

Sheet README
A1: MARUTI SUZUKI INDIA SALES DASHBOARD
A2: Project Overview | B2: Executive dashboard designed to analyze Maruti Suzuki India sales performance from 2021 to 2025 with interactive pivots, slicers, KPI cards and charts.
A3: Dataset Description | B3: Transaction-level sales data with date, geography, dealer, model, segment, fuel type, units sold, selling price, revenue, discount, profit, customer type, payment mode, rating and delivery days.
A4: KPIs Included | B4: Total Revenue, Total Units Sold, Total Profit, Average Selling Price, Average Customer Rating, Average Delivery Days, Total Discount, Number of Dealers
A5: Dashboard Usage | B5: Use the slicers on the dashboard to filter the analysis by Year, Month, Region, State, City, Car Model, Segment, Fuel Type, Customer Type and Payment Mode.
A6: Sheets | B6: README, Raw Data, Pivot Tables, Dashboard
A7: Author | B7: Jai Bhagwan
A8: Role | B8: Data Analyst Portfolio Project
A9: Tools Used | B9: Microsoft Excel, Pivot Tables, Pivot Charts, Slicers, Conditional Formatting
A10: Version | B10: v1.0 | Generated on 11-Jul-2026
A11: Interactivity Note | B11: Filters use data-validation dropdowns (not native Slicers) driving SUMIFS/AVERAGEIFS formulas and native charts, ensuring full interactivity and 100% compatibility across Excel 2019, 2021 LTSC, and Microsoft 365 without risk of corrupted slicer caches.

Sheet Lists
A1: Year | B1: Month | C1: Region | D1: State | E1: City | F1: Dealer Name | G1: Car Model | H1: Segment | I1: Fuel Type | J1: Customer Type | K1: Payment Mode
A2: All | B2: All | C2: All | D2: All | E2: All | F2: All | G2: All | H2: All | I2: All | J2: All | K2: All
A3: 2021 | B3: 1 | C3: East | D3: Delhi | E3: Ahmedabad | F3: Ahmedabad Motors | G3: Alto K10 | H3: Hatchback | I3: CNG | J3: Corporate | K3: Cash
A4: 2022 | B4: 2 | C4: North | D4: Gujarat | E4: Bengaluru | F4: Bengaluru Motors | G4: Baleno | H4: MPV | I4: Hybrid | J4: Individual | K4: EMI
A5: 2023 | B5: 3 | C5: South | D5: Karnataka | E5: Chennai | F5: Chennai Motors | G5: Brezza | H5: SUV | I5: Petrol | K5: Loan
A6: 2024 | B6: 4 | C6: West | D6: Maharashtra | E6: Delhi | F6: Delhi Motors | G6: Celerio | H6: Sedan
A7: 2025 | B7: 5 | D7: Tamil Nadu | E7: Hyderabad | F7: Hyderabad Motors | G7: Dzire | H7: Van
B8: 6 | D8: Telangana | E8: Kolkata | F8: Kolkata Motors | G8: Eeco
B9: 7 | D9: Uttar Pradesh | E9: Lucknow | F9: Lucknow Motors | G9: Ertiga
B10: 8 | D10: West Bengal | E10: Mumbai | F10: Mumbai Motors | G10: Fronx
B11: 9 | G11: Grand Vitara
B12: 10 | G12: Swift
B13: 11 | G13: WagonR
B14: 12 | G14: XL6

Sheet Calc
A1: Year | B1: Month | C1: Label | D1: Revenue | F1: Car Model | G1: Revenue | I1: Region | J1: Revenue | K1: Profit | M1: Fuel Type | N1: Revenue | P1: Segment | Q1: Revenue | S1: Dealer | T1: Revenue | U1: Rank | V1: Dealer (sorted) | W1: Revenue (sorted) | Y1: Payment Mode | Z1: Revenue | AB1: State | AC1: Revenue | AE1: Car Model | AF1: Avg Rating | AH1: Region | AI1: Avg Delivery Days
A2: 2021 | B2: 1 | C2: =TEXT(DATE(A2,B2,1),"mmm-yy") -> Jan-21 | D2: =SUMIFS('Raw Data'!$M$2:$M$3001,'Raw Data'!$T$2:$T$3001,1,'Raw Data'!$B$2:$B$3001,A2,'Raw Data'!$C$2:$C$3001,B2) -> 717868954 | F2: Alto K10 | G2: =SUMIFS('Raw Data'!$M$2:$M$3001,'Raw Data'!$T$2:$T$3001,1,'Raw Data'!$H$2:$H$3001,F2) -> 1851117985 | I2: East | J2: =SUMIFS('Raw Data'!$M$2:$M$3001,'Raw Data'!$T$2:$T$3001,1,'Raw Data'!$D$2:$D$3001,I2) -> 4555627781 | K2: =SUMIFS('Raw Data'!$O$2:$O$3001,'Raw Data'!$T$2:$T$3001,1,'Raw Data'!$D$2:$D$3001,I2) -> 5.4411774e+08 | M2: CNG | N2: =SUMIFS('Raw Data'!$M$2:$M$3001,'Raw Data'!$T$2:$T$3001,1,'Raw Data'!$J$2:$J$3001,M2) -> 13480913513 | P2: Hatchback | Q2: =SUMIFS('Raw Data'!$M$2:$M$3001,'Raw Data'!$T$2:$T$3001,1,'Raw Data'!$I$2:$I$3001,P2) -> 12518682521 | S2: Ahmedabad Motors | T2: =SUMIFS('Raw Data'!$M$2:$M$3001,'Raw Data'!$T$2:$T$3001,1,'Raw Data'!$G$2:$G$3001,S2) -> 5171580078 | U2: =RANK(T2,$T$2:$T$9)+COUNTIF($T$2:T2,T2)-1 -> 3 | V2: =IFERROR(INDEX($S$2:$S$9,MATCH(1,$U$2:$U$9,0)),"") -> Delhi Motors | W2: =IFERROR(INDEX($T$2:$T$9,MATCH(1,$U$2:$U$9,0)),0) -> 5493150571 | Y2: Cash | Z2: =SUMIFS('Raw Data'!$M$2:$M$3001,'Raw Data'!$T$2:$T$3001,1,'Raw Data'!$Q$2:$Q$3001,Y2) -> 14609841203 | AB2: Delhi | AC2: =SUMIFS('Raw Data'!$M$2:$M$3001,'Raw Data'!$T$2:$T$3001,1,'Raw Data'!$E$2:$E$3001,AB2) -> 5493150571 | AE2: Alto K10 | AF2: =IFERROR(AVERAGEIFS('Raw Data'!$R$2:$R$3001,'Raw Data'!$T$2:$T$3001,1,'Raw Data'!$H$2:$H$3001,AE2),0) -> 4.2287879 | AH2: East | AI2: =IFERROR(AVERAGEIFS('Raw Data'!$S$2:$S$3001,'Raw Data'!$T$2:$T$3001,1,'Raw Data'!$D$2:$D$3001,AH2),0) -> 11.78022
A3: 2021 | B3: 2 | C3: =TEXT(DATE(A3,B3,1),"mmm-yy") -> Feb-21 | D3: =SUMIFS('Raw Data'!$M$2:$M$3001,'Raw Data'!$T$2:$T$3001,1,'Raw Data'!$B$2:$B$3001,A3,'Raw Data'!$C$2:$C$3001,B3) -> 740795113 | F3: Baleno | G3: =SUMIFS('Raw Data'!$M$2:$M$3001,'Raw Data'!$T$2:$T$3001,1,'Raw Data'!$H$2:$H$3001,F3) -> 2887086025 | I3: North | J3: =SUMIFS('Raw Data'!$M$2:$M$3001,'Raw Data'!$T$2:$T$3001,1,'Raw Data'!$D$2:$D$3001,I3) -> 10570223699 | K3: =SUMIFS('Raw Data'!$O$2:$O$3001,'Raw Data'!$T$2:$T$3001,1,'Raw Data'!$D$2:$D$3001,I3) -> 1.2700599e+09 | M3: Hybrid | N3: =SUMIFS('Raw Data'!$M$2:$M$3001,'Raw Data'!$T$2:$T$3001,1,'Raw Data'!$J$2:$J$3001,M3) -> 6358472706 | P3: MPV | Q3: =SUMIFS('Raw Data'!$M$2:$M$3001,'Raw Data'!$T$2:$T$3001,1,'Raw Data'!$I$2:$I$3001,P3) -> 9021461104 | S3: Bengaluru Motors | T3: =SUMIFS('Raw Data'!$M$2:$M$3001,'Raw Data'!$T$2:$T$3001,1,'Raw Data'!$G$2:$G$3001,S3) -> 5099121391 | U3: =RANK(T3,$T$2:$T$9)+COUNTIF($T$2:T3,T3)-1 -> 4 | V3: =IFERROR(INDEX($S$2:$S$9,MATCH(2,$U$2:$U$9,0)),"") -> Hyderabad Motors | W3: =IFERROR(INDEX($T$2:$T$9,MATCH(2,$U$2:$U$9,0)),0) -> 5483356511 | Y3: EMI | Z3: =SUMIFS('Raw Data'!$M$2:$M$3001,'Raw Data'!$T$2:$T$3001,1,'Raw Data'!$Q$2:$Q$3001,Y3) -> 11820283687 | AB3: Gujarat | AC3: =SUMIFS('Raw Data'!$M$2:$M$3001,'Raw Data'!$T$2:$T$3001,1,'Raw Data'!$E$2:$E$3001,AB3) -> 5171580078 | AE3: Baleno | AF3: =IFERROR(AVERAGEIFS('Raw Data'!$R$2:$R$3001,'Raw Data'!$T$2:$T$3001,1,'Raw Data'!$H$2:$H$3001,AE3),0) -> 4.1675 | AH3: North | AI3: =IFERROR(AVERAGEIFS('Raw Data'!$S$2:$S$3001,'Raw Data'!$T$2:$T$3001,1,'Raw Data'!$D$2:$D$3001,AH3),0) -> 11.414573
A4: 2021 | B4: 3 | C4: =TEXT(DATE(A4,B4,1),"mmm-yy") -> Mar-21 | D4: =SUMIFS('Raw Data'!$M$2:$M$3001,'Raw Data'!$T$2:$T$3001,1,'Raw Data'!$B$2:$B$3001,A4,'Raw Data'!$C$2:$C$3001,B4) -> 805752152 | F4: Brezza | G4: =SUMIFS('Raw Data'!$M$2:$M$3001,'Raw Data'!$T$2:$T$3001,1,'Raw Data'!$H$2:$H$3001,F4) -> 3874335475 | I4: South | J4: =SUMIFS('Raw Data'!$M$2:$M$3001,'Raw Data'!$T$2:$T$3001,1,'Raw Data'!$D$2:$D$3001,I4) -> 15446471439 | K4: =SUMIFS('Raw Data'!$O$2:$O$3001,'Raw Data'!$T$2:$T$3001,1,'Raw Data'!$D$2:$D$3001,I4) -> 1.8648253e+09 | M4: Petrol | N4: =SUMIFS('Raw Data'!$M$2:$M$3001,'Raw Data'!$T$2:$T$3001,1,'Raw Data'!$J$2:$J$3001,M4) -> 20416490219 | P4: SUV | Q4: =SUMIFS('Raw Data'!$M$2:$M$3001,'Raw Data'!$T$2:$T$3001,1,'Raw Data'!$I$2:$I$3001,P4) -> 14063249481 | S4: Chennai Motors | T4: =SUMIFS('Raw Data'!$M$2:$M$3001,'Raw Data'!$T$2:$T$3001,1,'Raw Data'!$G$2:$G$3001,S4) -> 4863993537 | U4: =RANK(T4,$T$2:$T$9)+COUNTIF($T$2:T4,T4)-1 -> 6 | V4: =IFERROR(INDEX($S$2:$S$9,MATCH(3,$U$2:$U$9,0)),"") -> Ahmedabad Motors | W4: =IFERROR(INDEX($T$2:$T$9,MATCH(3,$U$2:$U$9,0)),0) -> 5171580078 | Y4: Loan | Z4: =SUMIFS('Raw Data'!$M$2:$M$3001,'Raw Data'!$T$2:$T$3001,1,'Raw Data'!$Q$2:$Q$3001,Y4) -> 13825751548 | AB4: Karnataka | AC4: =SUMIFS('Raw Data'!$M$2:$M$3001,'Raw Data'!$T$2:$T$3001,1,'Raw Data'!$E$2:$E$3001,AB4) -> 5099121391 | AE4: Brezza | AF4: =IFERROR(AVERAGEIFS('Raw Data'!$R$2:$R$3001,'Raw Data'!$T$2:$T$3001,1,'Raw Data'!$H$2:$H$3001,AE4),0) -> 4.2432836 | AH4: South | AI4: =IFERROR(AVERAGEIFS('Raw Data'!$S$2:$S$3001,'Raw Data'!$T$2:$T$3001,1,'Raw Data'!$D$2:$D$3001,AH4),0) -> 11.619211
A5: 2021 | B5: 4 | C5: =TEXT(DATE(A5,B5,1),"mmm-yy") -> Apr-21 | D5: =SUMIFS('Raw Data'!$M$2:$M$3001,'Raw Data'!$T$2:$T$3001,1,'Raw Data'!$B$2:$B$3001,A5,'Raw Data'!$C$2:$C$3001,B5) -> 714953762 | F5: Celerio | G5: =SUMIFS('Raw Data'!$M$2:$M$3001,'Raw Data'!$T$2:$T$3001,1,'Raw Data'!$H$2:$H$3001,F5) -> 2640789699 | I5: West | J5: =SUMIFS('Raw Data'!$M$2:$M$3001,'Raw Data'!$T$2:$T$3001,1,'Raw Data'!$D$2:$D$3001,I5) -> 9683553519 | K5: =SUMIFS('Raw Data'!$O$2:$O$3001,'Raw Data'!$T$2:$T$3001,1,'Raw Data'!$D$2:$D$3001,I5) -> 1.1525448e+09 | P5: Sedan | Q5: =SUMIFS('Raw Data'!$M$2:$M$3001,'Raw Data'!$T$2:$T$3001,1,'Raw Data'!$I$2:$I$3001,P5) -> 2565527215 | S5: Delhi Motors | T5: =SUMIFS('Raw Data'!$M$2:$M$3001,'Raw Data'!$T$2:$T$3001,1,'Raw Data'!$G$2:$G$3001,S5) -> 5493150571 | U5: =RANK(T5,$T$2:$T$9)+COUNTIF($T$2:T5,T5)-1 -> 1 | V5: =IFERROR(INDEX($S$2:$S$9,MATCH(4,$U$2:$U$9,0)),"") -> Bengaluru Motors | W5: =IFERROR(INDEX($T$2:$T$9,MATCH(4,$U$2:$U$9,0)),0) -> 5099121391 | AB5: Maharashtra | AC5: =SUMIFS('Raw Data'!$M$2:$M$3001,'Raw Data'!$T$2:$T$3001,1,'Raw Data'!$E$2:$E$3001,AB5) -> 4511973441 | AE5: Celerio | AF5: =IFERROR(AVERAGEIFS('Raw Data'!$R$2:$R$3001,'Raw Data'!$T$2:$T$3001,1,'Raw Data'!$H$2:$H$3001,AE5),0) -> 4.2971014 | AH5: West | AI5: =IFERROR(AVERAGEIFS('Raw Data'!$S$2:$S$3001,'Raw Data'!$T$2:$T$3001,1,'Raw Data'!$D$2:$D$3001,AH5),0) -> 12.024793
A6: 2021 | B6: 5 | C6: =TEXT(DATE(A6,B6,1),"mmm-yy") -> May-21 | D6: =SUMIFS('Raw Data'!$M$2:$M$3001,'Raw Data'!$T$2:$T$3001,1,'Raw Data'!$B$2:$B$3001,A6,'Raw Data'!$C$2:$C$3001,B6) -> 656482760 | F6: Dzire | G6: =SUMIFS('Raw Data'!$M$2:$M$3001,'Raw Data'!$T$2:$T$3001,1,'Raw Data'!$H$2:$H$3001,F6) -> 2565527215 | P6: Van | Q6: =SUMIFS('Raw Data'!$M$2:$M$3001,'Raw Data'!$T$2:$T$3001,1,'Raw Data'!$I$2:$I$3001,P6) -> 2086956117 | S6: Hyderabad Motors | T6: =SUMIFS('Raw Data'!$M$2:$M$3001,'Raw Data'!$T$2:$T$3001,1,'Raw Data'!$G$2:$G$3001,S6) -> 5483356511 | U6: =RANK(T6,$T$2:$T$9)+COUNTIF($T$2:T6,T6)-1 -> 2 | V6: =IFERROR(INDEX($S$2:$S$9,MATCH(5,$U$2:$U$9,0)),"") -> Lucknow Motors | W6: =IFERROR(INDEX($T$2:$T$9,MATCH(5,$U$2:$U$9,0)),0) -> 5077073128 | AB6: Tamil Nadu | AC6: =SUMIFS('Raw Data'!$M$2:$M$3001,'Raw Data'!$T$2:$T$3001,1,'Raw Data'!$E$2:$E$3001,AB6) -> 4863993537 | AE6: Dzire | AF6: =IFERROR(AVERAGEIFS('Raw Data'!$R$2:$R$3001,'Raw Data'!$T$2:$T$3001,1,'Raw Data'!$H$2:$H$3001,AE6),0) -> 4.2513514
A7: 2021 | B7: 6 | C7: =TEXT(DATE(A7,B7,1),"mmm-yy") -> Jun-21 | D7: =SUMIFS('Raw Data'!$M$2:$M$3001,'Raw Data'!$T$2:$T$3001,1,'Raw Data'!$B$2:$B$3001,A7,'Raw Data'!$C$2:$C$3001,B7) -> 635790349 | F7: Eeco | G7: =SUMIFS('Raw Data'!$M$2:$M$3001,'Raw Data'!$T$2:$T$3001,1,'Raw Data'!$H$2:$H$3001,F7) -> 2086956117 | S7: Kolkata Motors | T7: =SUMIFS('Raw Data'!$M$2:$M$3001,'Raw Data'!$T$2:$T$3001,1,'Raw Data'!$G$2:$G$3001,S7) -> 4555627781 | U7: =RANK(T7,$T$2:$T$9)+COUNTIF($T$2:T7,T7)-1 -> 7 | V7: =IFERROR(INDEX($S$2:$S$9,MATCH(6,$U$2:$U$9,0)),"") -> Chennai Motors | W7: =IFERROR(INDEX($T$2:$T$9,MATCH(6,$U$2:$U$9,0)),0) -> 4863993537 | AB7: Telangana | AC7: =SUMIFS('Raw Data'!$M$2:$M$3001,'Raw Data'!$T$2:$T$3001,1,'Raw Data'!$E$2:$E$3001,AB7) -> 5483356511 | AE7: Eeco | AF7: =IFERROR(AVERAGEIFS('Raw Data'!$R$2:$R$3001,'Raw Data'!$T$2:$T$3001,1,'Raw Data'!$H$2:$H$3001,AE7),0) -> 4.2647541
A8: 2021 | B8: 7 | C8: =TEXT(DATE(A8,B8,1),"mmm-yy") -> Jul-21 | D8: =SUMIFS('Raw Data'!$M$2:$M$3001,'Raw Data'!$T$2:$T$3001,1,'Raw Data'!$B$2:$B$3001,A8,'Raw Data'!$C$2:$C$3001,B8) -> 613209547 | F8: Ertiga | G8: =SUMIFS('Raw Data'!$M$2:$M$3001,'Raw Data'!$T$2:$T$3001,1,'Raw Data'!$H$2:$H$3001,F8) -> 3686612169 | S8: Lucknow Motors | T8: =SUMIFS('Raw Data'!$M$2:$M$3001,'Raw Data'!$T$2:$T$3001,1,'Raw Data'!$G$2:$G$3001,S8) -> 5077073128 | U8: =RANK(T8,$T$2:$T$9)+COUNTIF($T$2:T8,T8)-1 -> 5 | V8: =IFERROR(INDEX($S$2:$S$9,MATCH(7,$U$2:$U$9,0)),"") -> Kolkata Motors | W8: =IFERROR(INDEX($T$2:$T$9,MATCH(7,$U$2:$U$9,0)),0) -> 4555627781 | AB8: Uttar Pradesh | AC8: =SUMIFS('Raw Data'!$M$2:$M$3001,'Raw Data'!$T$2:$T$3001,1,'Raw Data'!$E$2:$E$3001,AB8) -> 5077073128 | AE8: Ertiga | AF8: =IFERROR(AVERAGEIFS('Raw Data'!$R$2:$R$3001,'Raw Data'!$T$2:$T$3001,1,'Raw Data'!$H$2:$H$3001,AE8),0) -> 4.2689655
A9: 2021 | B9: 8 | C9: =TEXT(DATE(A9,B9,1),"mmm-yy") -> Aug-21 | D9: =SUMIFS('Raw Data'!$M$2:$M$3001,'Raw Data'!$T$2:$T$3001,1,'Raw Data'!$B$2:$B$3001,A9,'Raw Data'!$C$2:$C$3001,B9) -> 607835973 | F9: Fronx | G9: =SUMIFS('Raw Data'!$M$2:$M$3001,'Raw Data'!$T$2:$T$3001,1,'Raw Data'!$H$2:$H$3001,F9) -> 3830441300 | S9: Mumbai Motors | T9: =SUMIFS('Raw Data'!$M$2:$M$3001,'Raw Data'!$T$2:$T$3001,1,'Raw Data'!$G$2:$G$3001,S9) -> 4511973441 | U9: =RANK(T9,$T$2:$T$9)+COUNTIF($T$2:T9,T9)-1 -> 8 | V9: =IFERROR(INDEX($S$2:$S$9,MATCH(8,$U$2:$U$9,0)),"") -> Mumbai Motors | W9: =IFERROR(INDEX($T$2:$T$9,MATCH(8,$U$2:$U$9,0)),0) -> 4511973441 | AB9: West Bengal | AC9: =SUMIFS('Raw Data'!$M$2:$M$3001,'Raw Data'!$T$2:$T$3001,1,'Raw Data'!$E$2:$E$3001,AB9) -> 4555627781 | AE9: Fronx | AF9: =IFERROR(AVERAGEIFS('Raw Data'!$R$2:$R$3001,'Raw Data'!$T$2:$T$3001,1,'Raw Data'!$H$2:$H$3001,AE9),0) -> 4.2575758
A10: 2021 | B10: 9 | C10: =TEXT(DATE(A10,B10,1),"mmm-yy") -> Sep-21 | D10: =SUMIFS('Raw Data'!$M$2:$M$3001,'Raw Data'!$T$2:$T$3001,1,'Raw Data'!$B$2:$B$3001,A10,'Raw Data'!$C$2:$C$3001,B10) -> 580651649 | F10: Grand Vitara | G10: =SUMIFS('Raw Data'!$M$2:$M$3001,'Raw Data'!$T$2:$T$3001,1,'Raw Data'!$H$2:$H$3001,F10) -> 6358472706 | AE10: Grand Vitara | AF10: =IFERROR(AVERAGEIFS('Raw Data'!$R$2:$R$3001,'Raw Data'!$T$2:$T$3001,1,'Raw Data'!$H$2:$H$3001,AE10),0) -> 4.319403
A11: 2021 | B11: 10 | C11: =TEXT(DATE(A11,B11,1),"mmm-yy") -> Oct-21 | D11: =SUMIFS('Raw Data'!$M$2:$M$3001,'Raw Data'!$T$2:$T$3001,1,'Raw Data'!$B$2:$B$3001,A11,'Raw Data'!$C$2:$C$3001,B11) -> 622895915 | F11: Swift | G11: =SUMIFS('Raw Data'!$M$2:$M$3001,'Raw Data'!$T$2:$T$3001,1,'Raw Data'!$H$2:$H$3001,F11) -> 2638660499 | AE11: Swift | AF11: =IFERROR(AVERAGEIFS('Raw Data'!$R$2:$R$3001,'Raw Data'!$T$2:$T$3001,1,'Raw Data'!$H$2:$H$3001,AE11),0) -> 4.2835937
A12: 2021 | B12: 11 | C12: =TEXT(DATE(A12,B12,1),"mmm-yy") -> Nov-21 | D12: =SUMIFS('Raw Data'!$M$2:$M$3001,'Raw Data'!$T$2:$T$3001,1,'Raw Data'!$B$2:$B$3001,A12,'Raw Data'!$C$2:$C$3001,B12) -> 645116964 | F12: WagonR | G12: =SUMIFS('Raw Data'!$M$2:$M$3001,'Raw Data'!$T$2:$T$3001,1,'Raw Data'!$H$2:$H$3001,F12) -> 2501028313 | AE12: WagonR | AF12: =IFERROR(AVERAGEIFS('Raw Data'!$R$2:$R$3001,'Raw Data'!$T$2:$T$3001,1,'Raw Data'!$H$2:$H$3001,AE12),0) -> 4.3039683
A13: 2021 | B13: 12 | C13: =TEXT(DATE(A13,B13,1),"mmm-yy") -> Dec-21 | D13: =SUMIFS('Raw Data'!$M$2:$M$3001,'Raw Data'!$T$2:$T$3001,1,'Raw Data'!$B$2:$B$3001,A13,'Raw Data'!$C$2:$C$3001,B13) -> 733668086 | F13: XL6 | G13: =SUMIFS('Raw Data'!$M$2:$M$3001,'Raw Data'!$T$2:$T$3001,1,'Raw Data'!$H$2:$H$3001,F13) -> 5334848935 | AE13: XL6 | AF13: =IFERROR(AVERAGEIFS('Raw Data'!$R$2:$R$3001,'Raw Data'!$T$2:$T$3001,1,'Raw Data'!$H$2:$H$3001,AE13),0) -> 4.2481203
A14: 2022 | B14: 1 | C14: =TEXT(DATE(A14,B14,1),"mmm-yy") -> Jan-22 | D14: =SUMIFS('Raw Data'!$M$2:$M$3001,'Raw Data'!$T$2:$T$3001,1,'Raw Data'!$B$2:$B$3001,A14,'Raw Data'!$C$2:$C$3001,B14) -> 624989756
A15: 2022 | B15: 2 | C15: =TEXT(DATE(A15,B15,1),"mmm-yy") -> Feb-22 | D15: =SUMIFS('Raw Data'!$M$2:$M$3001,'Raw Data'!$T$2:$T$3001,1,'Raw Data'!$B$2:$B$3001,A15,'Raw Data'!$C$2:$C$3001,B15) -> 483584875
A16: 2022 | B16: 3 | C16: =TEXT(DATE(A16,B16,1),"mmm-yy") -> Mar-22 | D16: =SUMIFS('Raw Data'!$M$2:$M$3001,'Raw Data'!$T$2:$T$3001,1,'Raw Data'!$B$2:$B$3001,A16,'Raw Data'!$C$2:$C$3001,B16) -> 666135918
A17: 2022 | B17: 4 | C17: =TEXT(DATE(A17,B17,1),"mmm-yy") -> Apr-22 | D17: =SUMIFS('Raw Data'!$M$2:$M$3001,'Raw Data'!$T$2:$T$3001,1,'Raw Data'!$B$2:$B$3001,A17,'Raw Data'!$C$2:$C$3001,B17) -> 631406516
A18: 2022 | B18: 5 | C18: =TEXT(DATE(A18,B18,1),"mmm-yy") -> May-22 | D18: =SUMIFS('Raw Data'!$M$2:$M$3001,'Raw Data'!$T$2:$T$3001,1,'Raw Data'!$B$2:$B$3001,A18,'Raw Data'!$C$2:$C$3001,B18) -> 684286087
A19: 2022 | B19: 6 | C19: =TEXT(DATE(A19,B19,1),"mmm-yy") -> Jun-22 | D19: =SUMIFS('Raw Data'!$M$2:$M$3001,'Raw Data'!$T$2:$T$3001,1,'Raw Data'!$B$2:$B$3001,A19,'Raw Data'!$C$2:$C$3001,B19) -> 541292728
A20: 2022 | B20: 7 | C20: =TEXT(DATE(A20,B20,1),"mmm-yy") -> Jul-22 | D20: =SUMIFS('Raw Data'!$M$2:$M$3001,'Raw Data'!$T$2:$T$3001,1,'Raw Data'!$B$2:$B$3001,A20,'Raw Data'!$C$2:$C$3001,B20) -> 780106068
A21: 2022 | B21: 8 | C21: =TEXT(DATE(A21,B21,1),"mmm-yy") -> Aug-22 | D21: =SUMIFS('Raw Data'!$M$2:$M$3001,'Raw Data'!$T$2:$T$3001,1,'Raw Data'!$B$2:$B$3001,A21,'Raw Data'!$C$2:$C$3001,B21) -> 681137586
A22: 2022 | B22: 9 | C22: =TEXT(DATE(A22,B22,1),"mmm-yy") -> Sep-22 | D22: =SUMIFS('Raw Data'!$M$2:$M$3001,'Raw Data'!$T$2:$T$3001,1,'Raw Data'!$B$2:$B$3001,A22,'Raw Data'!$C$2:$C$3001,B22) -> 764862343
A23: 2022 | B23: 10 | C23: =TEXT(DATE(A23,B23,1),"mmm-yy") -> Oct-22 | D23: =SUMIFS('Raw Data'!$M$2:$M$3001,'Raw Data'!$T$2:$T$3001,1,'Raw Data'!$B$2:$B$3001,A23,'Raw Data'!$C$2:$C$3001,B23) -> 705520597
A24: 2022 | B24: 11 | C24: =TEXT(DATE(A24,B24,1),"mmm-yy") -> Nov-22 | D24: =SUMIFS('Raw Data'!$M$2:$M$3001,'Raw Data'!$T$2:$T$3001,1,'Raw Data'!$B$2:$B$3001,A24,'Raw Data'!$C$2:$C$3001,B24) -> 840586095
A25: 2022 | B25: 12 | C25: =TEXT(DATE(A25,B25,1),"mmm-yy") -> Dec-22 | D25: =SUMIFS('Raw Data'!$M$2:$M$3001,'Raw Data'!$T$2:$T$3001,1,'Raw Data'!$B$2:$B$3001,A25,'Raw Data'!$C$2:$C$3001,B25) -> 731717689
... A61: 2025 | B61: 12 | C61: =TEXT(DATE(A61,B61,1),"mmm-yy") -> Dec-25 | D61: =SUMIFS('Raw Data'!$M$2:$M$3001,'Raw Data'!$T$2:$T$3001,1,'Raw Data'!$B$2:$B$3001,A61,'Raw Data'!$C$2:$C$3001,B61) -> 875810117
